graphrag_lite/__init__.py
graphrag_lite/core.py
graphrag_lite/prompts.py
graphrag_lite/utils.py
graphrag_lite-0.1.3.dist-info/licenses/LICENSE
graphrag_lite-0.1.3.dist-info/METADATA
graphrag_lite-0.1.3.dist-info/WHEEL
graphrag_lite-0.1.3.dist-info/top_level.txt
graphrag_lite-0.1.3.dist-info/RECORD
