Metadata-Version: 2.4
Name: graphrag-lite
Version: 0.1.3
Summary: A minimal GraphRAG implementation in ~600 lines of Python code
Author-email: Xu Ming <xuming624@qq.com>
License: Apache License 2.0
Project-URL: Homepage, https://github.com/shibing624/graphrag-lite
Project-URL: Repository, https://github.com/shibing624/graphrag-lite
Project-URL: Documentation, https://github.com/shibing624/graphrag-lite#readme
Project-URL: Issues, https://github.com/shibing624/graphrag-lite/issues
Keywords: graphrag,rag,knowledge-graph,llm,nlp,openai
Classifier: Development Status :: 4 - Beta
Classifier: Intended Audience :: Developers
Classifier: Intended Audience :: Science/Research
Classifier: License :: OSI Approved :: Apache Software License
Classifier: Operating System :: OS Independent
Classifier: Programming Language :: Python :: 3
Classifier: Programming Language :: Python :: 3.10
Classifier: Programming Language :: Python :: 3.11
Classifier: Programming Language :: Python :: 3.12
Classifier: Topic :: Scientific/Engineering :: Artificial Intelligence
Classifier: Topic :: Text Processing :: Linguistic
Requires-Python: >=3.10
License-File: LICENSE
Requires-Dist: openai>=1.0.0
Requires-Dist: tiktoken>=0.5.0
Requires-Dist: numpy>=1.24.0
Requires-Dist: loguru>=0.7.0
Requires-Dist: tqdm>=4.60.0
Provides-Extra: dev
Requires-Dist: pytest>=7.0.0; extra == "dev"
Requires-Dist: ruff>=0.1.0; extra == "dev"
Dynamic: license-file
